tf_sdp-0.9.dist-info/DESCRIPTION.rst
tf_sdp-0.9.dist-info/METADATA
tf_sdp-0.9.dist-info/RECORD
tf_sdp-0.9.dist-info/WHEEL
tf_sdp-0.9.dist-info/metadata.json
tf_sdp-0.9.dist-info/top_level.txt
tfsdp/__init__.py
tfsdp/datasets.py
tfsdp/models.py
tfsdp/utils.py
