Metadata-Version: 2.0
Name: tf-sdp
Version: 0.9
Summary: Deep Nonparametric Estimation of Discrete Conditional Distributions via Smoothed Dyadic Partitioning
Home-page: https://github.com/tansey/sdp
Author: Wesley Tansey
Author-email: wes.tansey@gmail.com
License: LGPL
Keywords: statistics machinelearning tensorflow deeplearning smoothing
Platform: UNKNOWN
Classifier: Development Status :: 3 - Alpha
Classifier: Intended Audience :: Science/Research
Classifier: Topic :: Scientific/Engineering
Classifier: License :: OSI Approved :: GNU Lesser General Public License v3 or later (LGPLv3+)
Classifier: Programming Language :: Python :: 2
Classifier: Programming Language :: Python :: 2.7
Requires-Dist: numpy
Requires-Dist: scipy
Requires-Dist: tensorflow
